setup.cfg
setup.py
digCollaborativeExtractor/__init__.py
digCollaborativeExtractor/collaborative_extractor.py
digCollaborativeExtractor.egg-info/PKG-INFO
digCollaborativeExtractor.egg-info/SOURCES.txt
digCollaborativeExtractor.egg-info/dependency_links.txt
digCollaborativeExtractor.egg-info/requires.txt
digCollaborativeExtractor.egg-info/top_level.txt