Metadata-Version: 1.1
Name: digCollaborativeExtractor
Version: 0.1.6
Summary: digCollaborativeExtractor
Home-page: https://github.com/usc-isi-i2/dig-collaborative-extractor
Author: Majid Ghasemi-Gol
Author-email: ghasemig@gmail.com
License: UNKNOWN
Download-URL: https://github.com/usc-isi-i2/dig-dictionary-extractor
Platform: UNKNOWN
